setup.py
codeEDU/code_edu.py
codeedu.egg-info/PKG-INFO
codeedu.egg-info/SOURCES.txt
codeedu.egg-info/dependency_links.txt
codeedu.egg-info/entry_points.txt
codeedu.egg-info/not-zip-safe
codeedu.egg-info/requires.txt
codeedu.egg-info/top_level.txt