Metadata-Version: 1.1
Name: codeedu
Version: 0.19
Summary: a simple tool to pick a random github repo
Home-page: https://github.com/jxieeducation/codeEDU
Author: Jason Xie
Author-email: jxieeducation@berkeley.edu
License: BST
Keywords: github learn read code
Platform: UNKNOWN
Classifier: Development Status :: 3 - Alpha
Classifier: Programming Language :: Python :: 2.7
